cxg_query_enhancer/__init__.py
cxg_query_enhancer/enhancer.py
cxg_query_enhancer-0.2.0.dist-info/LICENSE
cxg_query_enhancer-0.2.0.dist-info/METADATA
cxg_query_enhancer-0.2.0.dist-info/WHEEL
cxg_query_enhancer-0.2.0.dist-info/RECORD
