Metadata-Version: 2.3
Name: cxg-query-enhancer
Version: 0.2.0
Summary: A Python library that enhances biological query by expanding terms (cell types, tissues, etc..) to include subtypes and parts using ontologies, ensuring comprehensive data retrieval.
Author: Caroline Eastwood
Author-email: ce12@sanger.ac.uk
Requires-Python: >=3.10,<3.12
Classifier: Programming Language :: Python :: 3
Classifier: Programming Language :: Python :: 3.10
Classifier: Programming Language :: Python :: 3.11
Requires-Dist: cellxgene-census (>=1.17.0,<2.0.0)
Requires-Dist: pandas (>=2.2.3,<3.0.0)
Requires-Dist: requests (>=2.32.3,<3.0.0)
Requires-Dist: sparqlwrapper (>=2.0.0,<3.0.0)
Project-URL: Homepage, https://github.com/Cellular-Semantics/cxg-query-enhancer
Project-URL: Repository, https://github.com/Cellular-Semantics/cxg-query-enhancer
